<simulation>
	<info>
		<name>Segregation Simulation</name>
		<author>Peter Moseley</author>
		<type>Segregation</type>
	</info>
	<config>
		<grid_shape>Square</grid_shape>
		<grid_edge>Finite</grid_edge>
		<grid_outline>Yes</grid_outline>
		<cell_placement>Location</cell_placement>
		<color_scheme>Default</color_scheme>
		<cell_neighbors>Cardinal</cell_neighbors>
		<sim_satisfaction_threshold>0.4</sim_satisfaction_threshold>
	</config>
	<grid width="10" height="5">
		<empty>
			<xVals>3 7 3 7 3 7 3 7 3 7</xVals>
			<yVals>0 0 1 1 2 2 3 3 4 4</yVals>
			<population_percent>0.2</population_percent>
		</empty>
		<teamA>
			<xVals>0 2 5 8 9 0 2 5 8 9 0 2 5 8 9 0 2 5 8 9 0 2 5 8 9</xVals>
			<yVals>0 0 0 0 0 1 1 1 1 1 2 2 2 2 2 3 3 3 3 3 4 4 4 4 4</yVals>
			<population_percent>0.4</population_percent>
		</teamA>
		<teamB>
			<xVals>1 4 6 1 4 6 1 4 6 1 4 6 1 4 6</xVals>
			<yVals>0 0 0 1 1 1 2 2 2 3 3 3 4 4 4</yVals>
			<population_percent>0.4</population_percent>
		</teamB>
	</grid>
</simulation>